pycrontab/__init__.py
pycrontab/__main__.py
pycrontab/config.py
pycrontab/errors.py
pycrontab/event.py
pycrontab/log.py
pycrontab/parser.py
pycrontab/test_cron.py
pycrontab/test_worker.py
pycrontab/worker.py
pycrontab-0.1.2.dist-info/METADATA
pycrontab-0.1.2.dist-info/RECORD
pycrontab-0.1.2.dist-info/WHEEL
pycrontab-0.1.2.dist-info/entry_points.txt
pycrontab-0.1.2.dist-info/top_level.txt
